varphi_interpreter/__init__.py
varphi_interpreter/cli.py
varphi_interpreter-2.0.16.dist-info/WHEEL
varphi_interpreter-2.0.16.dist-info/entry_points.txt
varphi_interpreter-2.0.16.dist-info/METADATA
varphi_interpreter-2.0.16.dist-info/RECORD
