Metadata-Version: 2.3
Name: varphi-interpreter
Version: 2.0.16
Summary: An all-in-one tool for compiling and interpreting Varphi programs.
Author: Varphi
Author-email: Varphi <support@varphi-lang.com>
Requires-Dist: typer>=0.21.0
Requires-Dist: varphi-python==2.0.6
Requires-Dist: varphi-python-dap==1.0.6
Requires-Python: >=3.13
